webssh_embedded/__init__.py
webssh_embedded/_version.py
webssh_embedded/handler.py
webssh_embedded/main.py
webssh_embedded/policy.py
webssh_embedded/settings.py
webssh_embedded/utils.py
webssh_embedded/worker.py
webssh_embedded/static/css/bootstrap.min.css
webssh_embedded/static/css/fullscreen.min.css
webssh_embedded/static/css/xterm.min.css
webssh_embedded/static/css/fonts/.gitignore
webssh_embedded/static/img/favicon.png
webssh_embedded/static/js/bootstrap.min.js
webssh_embedded/static/js/iframetest.html
webssh_embedded/static/js/jquery.min.js
webssh_embedded/static/js/main.js
webssh_embedded/static/js/popper.min.js
webssh_embedded/static/js/xterm-addon-fit.min.js
webssh_embedded/static/js/xterm.min.js
webssh_embedded/templates/index.html
webssh_embedded-1.1.4.dist-info/LICENSE
webssh_embedded-1.1.4.dist-info/METADATA
webssh_embedded-1.1.4.dist-info/WHEEL
webssh_embedded-1.1.4.dist-info/entry_points.txt
webssh_embedded-1.1.4.dist-info/top_level.txt
webssh_embedded-1.1.4.dist-info/RECORD
