Metadata-Version: 2.1
Name: webssh-embedded
Version: 1.1.4
Summary: Interactive embedded web terminal
Home-page: https://github.com/TXH2020/webssh_embedded
Author: Tejas Hegde
Author-email: 1001.tejas@gmail.com
License: MIT
Platform: UNKNOWN
Classifier: Programming Language :: Python
Classifier: Programming Language :: Python :: 3
Classifier: Programming Language :: Python :: 3.8
Classifier: Programming Language :: Python :: 3.9
Classifier: Programming Language :: Python :: 3.10
Classifier: Programming Language :: Python :: 3.11
License-File: LICENSE
Requires-Dist: paramiko (>=2.3.1)
Requires-Dist: requests
Requires-Dist: tornado (>=4.5.0)
